monasca_events_agent/main.py
monasca_events_agent-0.dist-info/DESCRIPTION.rst
monasca_events_agent-0.dist-info/METADATA
monasca_events_agent-0.dist-info/RECORD
monasca_events_agent-0.dist-info/WHEEL
monasca_events_agent-0.dist-info/entry_points.txt
monasca_events_agent-0.dist-info/metadata.json
monasca_events_agent-0.dist-info/top_level.txt
